md2bbcode/__init__.py
md2bbcode/html2bbcode.py
md2bbcode/main.py
md2bbcode/md2ast.py
md2bbcode/plugins/merge_lists.py
md2bbcode/renderers/__init__.py
md2bbcode/renderers/bbcode.py
md2bbcode-1.0.9.dist-info/METADATA
md2bbcode-1.0.9.dist-info/WHEEL
md2bbcode-1.0.9.dist-info/entry_points.txt
md2bbcode-1.0.9.dist-info/licenses/LICENSE.txt
md2bbcode-1.0.9.dist-info/RECORD
