Metadata-Version: 2.4
Name: md2bbcode
Version: 1.0.9
Summary: Convert Markdown to BBCode using a custom Mistune renderer.
Project-URL: Repository, https://github.com/RedGuides/md2bbcode.git
Project-URL: Issues, https://github.com/RedGuides/md2bbcode/issues
Project-URL: Documentation, https://github.com/RedGuides/md2bbcode#readme
Author-email: Redbot <ask@redguides.com>
License-Expression: GPL-3.0-or-later
License-File: LICENSE.txt
Classifier: Development Status :: 5 - Production/Stable
Classifier: Intended Audience :: Developers
Classifier: License :: OSI Approved :: GNU General Public License v3 or later (GPLv3+)
Classifier: Operating System :: OS Independent
Classifier: Programming Language :: Python :: 3
Classifier: Topic :: Text Processing :: Markup :: HTML
Classifier: Topic :: Text Processing :: Markup :: Markdown
Classifier: Topic :: Utilities
Requires-Dist: beautifulsoup4
Requires-Dist: mistune>=3.0.2
